scuti/__init__.py
scuti/domain/__init__.py
scuti/domain/errors.py
scuti/domain/cqrs/__init__.py
scuti/domain/cqrs/effects.py
scuti/domain/cqrs/bus/__init__.py
scuti/domain/cqrs/bus/command_bus.py
scuti/domain/cqrs/bus/effect_handler.py
scuti/domain/cqrs/bus/event_bus.py
scuti/domain/cqrs/bus/events.py
scuti/domain/cqrs/bus/exceptions.py
scuti/domain/cqrs/bus/query_bus.py
scuti/domain/cqrs/bus/query_handler.py
scuti/domain/cqrs/bus/hooks/__init__.py
scuti/domain/cqrs/bus/hooks/bus_hook.py
scuti/domain/cqrs/bus/hooks/logging_effects_bus_hook.py
scuti/domain/cqrs/bus/state_management/__init__.py
scuti/domain/cqrs/bus/state_management/commands.py
scuti/domain/cqrs/bus/state_management/condition.py
scuti/domain/cqrs/bus/state_management/dataclass.py
scuti/domain/cqrs/bus/state_management/effect_to_state_mapping.py
scuti/domain/cqrs/bus/state_management/evolve.py
scuti/domain/cqrs/effect_store/__init__.py
scuti/domain/cqrs/effect_store/effect_store.py
scuti/domain/cqrs/event_scheduler/__init__.py
scuti/domain/cqrs/event_scheduler/commands.py
scuti/domain/cqrs/event_scheduler/event_scheduler_handler.py
scuti/domain/cqrs/event_scheduler/events.py
scuti/domain/cqrs/event_scheduler/scheduled_events_store.py
scuti/domain/model/__init__.py
scuti/domain/model/modules.py
scuti/domain/model/application/__init__.py
scuti/domain/model/application/application_error.py
scuti/domain/model/application/domain_application.py
scuti/domain/model/application/net_config.py
scuti/domain/model/identifiable/__init__.py
scuti/domain/model/identifiable/identifiable_entity.py
scuti/domain/model/identifiable/identifier.py
scuti/domain/model/repository/__init__.py
scuti/domain/model/repository/repository.py
scuti/domain/model/store/__init__.py
scuti/domain/model/store/store.py
scuti/domain/testing/__init__.py
scuti/domain/testing/save_effects_bus_hook.py
scuti/domain/testing/testing_domain_module.py
scuti/domain/testing/matchers/__init__.py
scuti/domain/testing/matchers/any_id.py
scuti-0.0.3.dist-info/METADATA
scuti-0.0.3.dist-info/WHEEL
scuti-0.0.3.dist-info/licenses/LICENSE
scuti-0.0.3.dist-info/RECORD
