Metadata-Version: 2.1
Name: scuti
Version: 0.0.3
Summary: A simple backend framework for building complex web applications. Inspired in CQS and DDD
Project-URL: Homepage, https://github.com/jvalduvieco/scuti
Project-URL: Bug Tracker, https://github.com/jvalduvieco/scuti/issues
Author-email: Joan Valduvieco <jvalduvieco@gmail.com>
License-File: LICENSE
Classifier: Environment :: Web Environment
Classifier: Intended Audience :: Developers
Classifier: License :: OSI Approved :: MIT License
Classifier: Operating System :: OS Independent
Classifier: Programming Language :: Python
Classifier: Programming Language :: Python :: 3
Classifier: Topic :: Software Development :: Libraries :: Application Frameworks
Requires-Python: >=3.10
Requires-Dist: injector==0.20.1
Requires-Dist: plum-dispatch==1.7.4
Requires-Dist: uuid==1.30
